<?xml version="1.0" encoding="UTF-8"?>
<LanguageData>
  
  <!-- EN: blonde hair -->
  <Hair_Blonde.label>szőke haj</Hair_Blonde.label>
  <!-- EN: Carriers of this gene have a particular hair color. With multiple hair color genes, one is randomly selected. -->
  <Hair_Blonde.description>E gén hordozóinak sajátos hajszínük van. Több hajszín gén esetén az egyik véletlenszerűen kerül kiválasztásra.</Hair_Blonde.description>
  
  <!-- EN: red hair -->
  <Hair_BrightRed.label>vörös haj</Hair_BrightRed.label>
  <!-- EN: Carriers of this gene have a particular hair color. With multiple hair color genes, one is randomly selected. -->
  <Hair_BrightRed.description>E gén hordozóinak sajátos hajszínük van. Több hajszín gén esetén az egyik véletlenszerűen kerül kiválasztásra.</Hair_BrightRed.description>
  
  <!-- EN: dark-black hair -->
  <Hair_DarkBlack.label>sötétfekete haj</Hair_DarkBlack.label>
  <!-- EN: Carriers of this gene have a particular hair color. With multiple hair color genes, one is randomly selected. -->
  <Hair_DarkBlack.description>E gén hordozóinak sajátos hajszínük van. Több hajszín gén esetén az egyik véletlenszerűen kerül kiválasztásra.</Hair_DarkBlack.description>
  
  <!-- EN: brown hair -->
  <Hair_DarkBrown.label>barna haj</Hair_DarkBrown.label>
  <!-- EN: Carriers of this gene have a particular hair color. With multiple hair color genes, one is randomly selected. -->
  <Hair_DarkBrown.description>E gén hordozóinak sajátos hajszínük van. Több hajszín gén esetén az egyik véletlenszerűen kerül kiválasztásra.</Hair_DarkBrown.description>
  
  <!-- EN: dark-reddish hair -->
  <Hair_DarkReddish.label>sötétvörös haj</Hair_DarkReddish.label>
  <!-- EN: Carriers of this gene have a particular hair color. With multiple hair color genes, one is randomly selected. -->
  <Hair_DarkReddish.description>E gén hordozóinak sajátos hajszínük van. Több hajszín gén esetén az egyik véletlenszerűen kerül kiválasztásra.</Hair_DarkReddish.description>
  
  <!-- EN: dark-brown hair -->
  <Hair_DarkSaturatedReddish.label>sötétbarna haj</Hair_DarkSaturatedReddish.label>
  <!-- EN: Carriers of this gene have a particular hair color. With multiple hair color genes, one is randomly selected. -->
  <Hair_DarkSaturatedReddish.description>E gén hordozóinak sajátos hajszínük van. Több hajszín gén esetén az egyik véletlenszerűen kerül kiválasztásra.</Hair_DarkSaturatedReddish.description>
  
  <!-- EN: gray hair -->
  <Hair_Gray.label>szürke haj</Hair_Gray.label>
  <!-- EN: Carriers of this gene have a particular hair color. With multiple hair color genes, one is randomly selected. -->
  <Hair_Gray.description>E gén hordozóinak sajátos hajszínük van. Több hajszín gén esetén az egyik véletlenszerűen kerül kiválasztásra.</Hair_Gray.description>
  
  <!-- EN: ink-black hair -->
  <Hair_InkBlack.label>tintafekete haj</Hair_InkBlack.label>
  <!-- EN: Carriers of this gene have a particular hair color. With multiple hair color genes, one is randomly selected. -->
  <Hair_InkBlack.description>E gén hordozóinak sajátos hajszínük van. Több hajszín gén esetén az egyik véletlenszerűen kerül kiválasztásra.</Hair_InkBlack.description>
  
  <!-- EN: blue hair -->
  <Hair_LightBlue.label>kék haj</Hair_LightBlue.label>
  <!-- EN: Carriers of this gene have a particular hair color. With multiple hair color genes, one is randomly selected. -->
  <Hair_LightBlue.description>E gén hordozóinak sajátos hajszínük van. Több hajszín gén esetén az egyik véletlenszerűen kerül kiválasztásra.</Hair_LightBlue.description>
  
  <!-- EN: green hair -->
  <Hair_LightGreen.label>zöld haj</Hair_LightGreen.label>
  <!-- EN: Carriers of this gene have a particular hair color. With multiple hair color genes, one is randomly selected. -->
  <Hair_LightGreen.description>E gén hordozóinak sajátos hajszínük van. Több hajszín gén esetén az egyik véletlenszerűen kerül kiválasztásra.</Hair_LightGreen.description>
  
  <!-- EN: orange hair -->
  <Hair_LightOrange.label>narancssárga haj</Hair_LightOrange.label>
  <!-- EN: Carriers of this gene have a particular hair color. With multiple hair color genes, one is randomly selected. -->
  <Hair_LightOrange.description>E gén hordozóinak sajátos hajszínük van. Több hajszín gén esetén az egyik véletlenszerűen kerül kiválasztásra.</Hair_LightOrange.description>
  
  <!-- EN: purple hair -->
  <Hair_LightPurple.label>lila haj</Hair_LightPurple.label>
  <!-- EN: Carriers of this gene have a particular hair color. With multiple hair color genes, one is randomly selected. -->
  <Hair_LightPurple.description>E gén hordozóinak sajátos hajszínük van. Több hajszín gén esetén az egyik véletlenszerűen kerül kiválasztásra.</Hair_LightPurple.description>
  
  <!-- EN: teal hair -->
  <Hair_LightTeal.label>kékeszöld haj</Hair_LightTeal.label>
  <!-- EN: Carriers of this gene have a particular hair color. With multiple hair color genes, one is randomly selected. -->
  <Hair_LightTeal.description>E gén hordozóinak sajátos hajszínük van. Több hajszín gén esetén az egyik véletlenszerűen kerül kiválasztásra.</Hair_LightTeal.description>
  
  <!-- EN: mid-black hair -->
  <Hair_MidBlack.label>középfekete haj</Hair_MidBlack.label>
  <!-- EN: Carriers of this gene have a particular hair color. With multiple hair color genes, one is randomly selected. -->
  <Hair_MidBlack.description>E gén hordozóinak sajátos hajszínük van. Több hajszín gén esetén az egyik véletlenszerűen kerül kiválasztásra.</Hair_MidBlack.description>
  
  <!-- EN: pink hair -->
  <Hair_Pink.label>rózsaszín haj</Hair_Pink.label>
  <!-- EN: Carriers of this gene have a particular hair color. With multiple hair color genes, one is randomly selected. -->
  <Hair_Pink.description>E gén hordozóinak sajátos hajszínük van. Több hajszín gén esetén az egyik véletlenszerűen kerül kiválasztásra.</Hair_Pink.description>
  
  <!-- EN: reddish-brown hair -->
  <Hair_ReddishBrown.label>vörösesbarna haj</Hair_ReddishBrown.label>
  <!-- EN: Carriers of this gene have a particular hair color. With multiple hair color genes, one is randomly selected. -->
  <Hair_ReddishBrown.description>E gén hordozóinak sajátos hajszínük van. Több hajszín gén esetén az egyik véletlenszerűen kerül kiválasztásra.</Hair_ReddishBrown.description>
  
  <!-- EN: sandy-blonde hair -->
  <Hair_SandyBlonde.label>vörösesszőke haj</Hair_SandyBlonde.label>
  <!-- EN: Carriers of this gene have a particular hair color. With multiple hair color genes, one is randomly selected. -->
  <Hair_SandyBlonde.description>E gén hordozóinak sajátos hajszínük van. Több hajszín gén esetén az egyik véletlenszerűen kerül kiválasztásra.</Hair_SandyBlonde.description>
  
  <!-- EN: snow-white hair -->
  <Hair_SnowWhite.label>hófehér haj</Hair_SnowWhite.label>
  <!-- EN: Carriers of this gene have a particular hair color. With multiple hair color genes, one is randomly selected. -->
  <Hair_SnowWhite.description>E gén hordozóinak sajátos hajszínük van. Több hajszín gén esetén az egyik véletlenszerűen kerül kiválasztásra.</Hair_SnowWhite.description>
  
  <!-- EN: skin color -->
  <Skin_Melanin1.label>bőrszín</Skin_Melanin1.label>
  <!-- EN: Carriers of this gene have a particular skin color. With multiple skin color genes, one is randomly selected. -->
  <Skin_Melanin1.description>E gén hordozóinak sajátos bőrszínük van. Több bőrszín gén esetén az egyik véletlenszerűen kerül kiválasztásra.</Skin_Melanin1.description>
  
  <!-- EN: skin color -->
  <Skin_Melanin2.label>bőrszín</Skin_Melanin2.label>
  <!-- EN: Carriers of this gene have a particular skin color. With multiple skin color genes, one is randomly selected. -->
  <Skin_Melanin2.description>E gén hordozóinak sajátos bőrszínük van. Több bőrszín gén esetén az egyik véletlenszerűen kerül kiválasztásra.</Skin_Melanin2.description>
  
  <!-- EN: skin color -->
  <Skin_Melanin3.label>bőrszín</Skin_Melanin3.label>
  <!-- EN: Carriers of this gene have a particular skin color. With multiple skin color genes, one is randomly selected. -->
  <Skin_Melanin3.description>E gén hordozóinak sajátos bőrszínük van. Több bőrszín gén esetén az egyik véletlenszerűen kerül kiválasztásra.</Skin_Melanin3.description>
  
  <!-- EN: skin color -->
  <Skin_Melanin4.label>bőrszín</Skin_Melanin4.label>
  <!-- EN: Carriers of this gene have a particular skin color. With multiple skin color genes, one is randomly selected. -->
  <Skin_Melanin4.description>E gén hordozóinak sajátos bőrszínük van. Több bőrszín gén esetén az egyik véletlenszerűen kerül kiválasztásra.</Skin_Melanin4.description>
  
  <!-- EN: skin color -->
  <Skin_Melanin5.label>bőrszín</Skin_Melanin5.label>
  <!-- EN: Carriers of this gene have a particular skin color. With multiple skin color genes, one is randomly selected. -->
  <Skin_Melanin5.description>E gén hordozóinak sajátos bőrszínük van. Több bőrszín gén esetén az egyik véletlenszerűen kerül kiválasztásra.</Skin_Melanin5.description>
  
  <!-- EN: skin color -->
  <Skin_Melanin6.label>bőrszín</Skin_Melanin6.label>
  <!-- EN: Carriers of this gene have a particular skin color. With multiple skin color genes, one is randomly selected. -->
  <Skin_Melanin6.description>E gén hordozóinak sajátos bőrszínük van. Több bőrszín gén esetén az egyik véletlenszerűen kerül kiválasztásra.</Skin_Melanin6.description>
  
  <!-- EN: skin color -->
  <Skin_Melanin7.label>bőrszín</Skin_Melanin7.label>
  <!-- EN: Carriers of this gene have a particular skin color. With multiple skin color genes, one is randomly selected. -->
  <Skin_Melanin7.description>E gén hordozóinak sajátos bőrszínük van. Több bőrszín gén esetén az egyik véletlenszerűen kerül kiválasztásra.</Skin_Melanin7.description>
  
  <!-- EN: skin color -->
  <Skin_Melanin8.label>bőrszín</Skin_Melanin8.label>
  <!-- EN: Carriers of this gene have a particular skin color. With multiple skin color genes, one is randomly selected. -->
  <Skin_Melanin8.description>E gén hordozóinak sajátos bőrszínük van. Több bőrszín gén esetén az egyik véletlenszerűen kerül kiválasztásra.</Skin_Melanin8.description>
  
  <!-- EN: skin color -->
  <Skin_Melanin9.label>bőrszín</Skin_Melanin9.label>
  <!-- EN: Carriers of this gene have a particular skin color. With multiple skin color genes, one is randomly selected. -->
  <Skin_Melanin9.description>E gén hordozóinak sajátos bőrszínük van. Több bőrszín gén esetén az egyik véletlenszerűen kerül kiválasztásra.</Skin_Melanin9.description>
  
</LanguageData>