<?xml version="1.0" encoding="UTF-8"?>
<LanguageData>
  
  <!-- EN: essential -->
  <GrowthVat_Essential.label>alapvető</GrowthVat_Essential.label>
  <!-- EN: We have the technology for safer childbirth and faster childhoods. Believers will develop faster in growth vats but will be unhappy if their children are not in a vat. -->
  <GrowthVat_Essential.description>Rendelkezünk a biztonságosabb szüléshez és a gyorsabb gyermekkorhoz szükséges technológiával. A hívők gyorsabban fejlődnek a növesztő tartályokban, de boldogtalanok lesznek, ha gyermekeik nincsenek ott.</GrowthVat_Essential.description>
  <!-- EN: Natural pregnancy -->
  <GrowthVat_Essential.comps.0.description>Természetes terhesség</GrowthVat_Essential.comps.0.description>
  <!-- EN: Child not in growth vat -->
  <GrowthVat_Essential.comps.1.description>Gyermek nincs a növesztő tartályban</GrowthVat_Essential.comps.1.description>
  
  <!-- EN: prohibited -->
  <GrowthVat_Prohibited.label>tiltott</GrowthVat_Prohibited.label>
  <!-- EN: Growth vats rob children of their childhood. -->
  <GrowthVat_Prohibited.description>A növesztő tartályok megfosztják a gyermekeket gyermekkoruktól.</GrowthVat_Prohibited.description>
  <!-- EN: Build growth vat -->
  <GrowthVat_Prohibited.comps.0.description>Növesztő tartály építése</GrowthVat_Prohibited.comps.0.description>
  <!-- EN: Growth vat in colony -->
  <GrowthVat_Prohibited.comps.1.description>Növesztő tartály a kolóniában</GrowthVat_Prohibited.comps.1.description>
  <!-- EN: My child in a growth vat -->
  <GrowthVat_Prohibited.comps.2.description>Gyermekem egy növesztő tartályban</GrowthVat_Prohibited.comps.2.description>
  <!-- EN: Child not in growth vat -->
  <GrowthVat_Prohibited.comps.3.description>Gyermek nincs a növesztő tartályban</GrowthVat_Prohibited.comps.3.description>
  
</LanguageData>