<?xml version="1.0" encoding="UTF-8"?>
<LanguageData>
  <Work.label>munka</Work.label>
  <Meditative.label>meditatív</Meditative.label>
  <Lewd.label>buja</Lewd.label>
  <Social.label>szociális</Social.label>
  <Chemical.label>kémiai</Chemical.label>
  <Gluttonous.label>falánk</Gluttonous.label>
  <GamingDexterity.label>játék (ügyességi)</GamingDexterity.label>
  <GamingCerebral.label>játék (ész)</GamingCerebral.label>
  <Passive.label>passzív</Passive.label>
  <Study.label>tanulási</Study.label>
</LanguageData>
