<?xml version="1.0" encoding="UTF-8"?>
<LanguageData>
  <Mood.label>hangulat</Mood.label>
  <Mood.description>A hangulat határozza meg, hogy valaki mennyire boldog vagy zaklatott. Ha a hangulat nagyon leromlik, az alany idegösszeomlást kaphat.</Mood.description>
  <Food.label>étel</Food.label>
  <Food.description>Az étel mutatja, hogy mennyi tápanyagot vett magához az alany az utóbbi időben. Ha nullára csökken, akkor az éhezés miatt sebesülés lép fel.</Food.description>
  <Rest.label>pihenés</Rest.label>
  <Rest.description>A pihenés mutatja, hogy az utóbbi időben mennyit aludt az alany.</Rest.description>
  <Joy.label>élvezet</Joy.label>
  <Joy.description>Az élvezet mutatja annak a szükségességét, hogy valami olyat csináljunk, ami örömet okoz. Ugyanazt a tevékenységet ismételve csökken annak hatékonysága.</Joy.description>
  <Beauty.label>szépség</Beauty.label>
  <Beauty.description>A szépség mutatja, hogy az alany mennyire találja környezetét vizuálisan kielégítőnek.</Beauty.description>
  <Comfort.label>kényelem</Comfort.label>
  <Comfort.description>A kényelem növekszik, ha az alany kényelmes bútorokon ül illetve alszik.</Comfort.description>
  <!-- <Space.label>tér</Space.label> -->
  <!-- <Space.description>Ez mutatja a szabadság érzését és a szabad mozgás lehetőségét. Leromlik, ha hosszabb ideig van az alany zsúfolt szobában.</Space.description> -->
  
  <Outdoors.label>tér</Outdoors.label>
  <Outdoors.description>Ez mutatja a szabadság érzését és a szabad mozgás lehetőségét. Leromlik, ha hosszabb ideig van az alany zsúfolt szobában. főleg a föld alatt. Javul, ha valaki a szabad ég alatt tölt időt. Nem a szobák méretétől függ, hanem hogy időről-időre elhagyják azt. A szabadban töltött idő rövidségének kezelése kihívást jelent azok számára, akik a föld alatt élnek.</Outdoors.description>

  <RoomSize.label>szoba méret</RoomSize.label>
  
</LanguageData>
