<?xml version="1.0" encoding="UTF-8"?>
<LanguageData>
  
  <!-- EN: psychic animal pulser -->
  <PsychicAnimalPulser.label>Állatvadító</PsychicAnimalPulser.label>
  <!-- EN: A one-use broad-wave psychic effector. The psychic pulse fills lower minds with terrifying imagery, driving all animals in the region into a manhunting rage. Animals currently under your control will not be affected. -->
  <PsychicAnimalPulser.description>Egyszer használatos relikvia, ami a régióban lévő összes állatból emberevőt csinál.</PsychicAnimalPulser.description>
  <!-- EN: Activate -->
  <PsychicAnimalPulser.comps.CompUsable.useLabel>Állatvadító aktiválás</PsychicAnimalPulser.comps.CompUsable.useLabel>
  
  <!-- EN: psychic soothe pulser -->
  <PsychicSoothePulser.label>Nyugalomforrás</PsychicSoothePulser.label>
  <!-- EN: A one-use broad-wave psychic effector. The psychic pulse induces self-satisfying perceptual distortions, giving a temporary mood boost to everyone in the region. -->
  <PsychicSoothePulser.description>Egyszer használatos relikvia, a térképen lévő minden karakternél hangulatjavulást okoz.</PsychicSoothePulser.description>
  <!-- EN: Activate -->
  <PsychicSoothePulser.comps.CompUsable.useLabel>Nyugalomforrás aktiválás</PsychicSoothePulser.comps.CompUsable.useLabel>
  
</LanguageData>
